consecution/__init__.py
consecution/nodes.py
consecution/pipeline.py
consecution/utils.py
consecution/tests/__init__.py
consecution/tests/nodes_tests.py
consecution/tests/pipeline_tests.py
consecution/tests/testing_helpers.py
consecution/tests/utils_tests.py
consecution-0.2.0.dist-info/DESCRIPTION.rst
consecution-0.2.0.dist-info/METADATA
consecution-0.2.0.dist-info/metadata.json
consecution-0.2.0.dist-info/RECORD
consecution-0.2.0.dist-info/top_level.txt
consecution-0.2.0.dist-info/WHEEL
